ruslingua/__init__.py
ruslingua/ruslingua.py
ruslingua-1.0.1.dist-info/licenses/LICENSE
ruslingua-1.0.1.dist-info/METADATA
ruslingua-1.0.1.dist-info/WHEEL
ruslingua-1.0.1.dist-info/top_level.txt
ruslingua-1.0.1.dist-info/RECORD
